{
  "catalog_id": "chevrolet_colorado_pre",
  "title": "쉐보레 콜로라도",
  "maker": "쉐보레",
  "source": "stub",
  "source_urls": [],
  "fetched_at": "2026-05-04",
  "note": "페리 전/세대 분리 stub",
  "options": {},
  "categories": {},
  "trims": {
    "익스트림": {
      "slug": "익스트림",
      "price": {},
      "basic": [],
      "select": [],
      "select_groups": []
    },
    "Z71": {
      "slug": "z71",
      "price": {},
      "basic": [],
      "select": [],
      "select_groups": []
    },
    "LT": {
      "slug": "lt",
      "price": {},
      "basic": [],
      "select": [],
      "select_groups": []
    }
  },
  "aliases": [
    "콜로라도"
  ],
  "year_start": "2019-01",
  "year_end": "2020-12"
}